<?xml version="1.0" encoding="utf-8"?>
<NinjaTrader>
  <NTWindows>
    <Chart-611c4f7968004efcb3ec3ec19e478c73>
      <Class Assembly="NinjaTrader.Gui">NinjaTrader.Gui.Chart.Chart</Class>
      <WindowState>Normal</WindowState>
      <Location>0;0</Location>
      <Size>1280;720</Size>
      <ZOrder>0</ZOrder>
      <Topmost>False</Topmost>
      <TraderWidth>200</TraderWidth>
      <TabControl>
        <SelectedIndex>0</SelectedIndex>
        <Tab-be0949238d1340d3b8e565d0d5d9a57f>
          <InstrumentLink>0</InstrumentLink>
          <IntervalLink>0</IntervalLink>
          <DataSeries>
            <BarsProperties>
              <BarsProperties xmlns:xsd="http://www.w3.org/2001/XMLSchema" xmlns:xsi="http://www.w3.org/2001/XMLSchema-instance">
                <BarsPeriod>
                  <BarsPeriodTypeSerialize>1</BarsPeriodTypeSerialize>
                  <BaseBarsPeriodType>Minute</BaseBarsPeriodType>
                  <BaseBarsPeriodValue>1</BaseBarsPeriodValue>
                  <VolumetricDeltaType>BidAsk</VolumetricDeltaType>
                  <MarketDataType>Last</MarketDataType>
                  <PointAndFigurePriceType>Close</PointAndFigurePriceType>
                  <ReversalType>Tick</ReversalType>
                  <Value>5</Value>
                  <Value2>1</Value2>
                </BarsPeriod>
                <RangeType>Days</RangeType>
                <BarsBack>50</BarsBack>
                <DaysBack>60</DaysBack>
                <From>2026-01-01T00:00:00</From>
                <IsStableSession>true</IsStableSession>
                <IsTickReplay>false</IsTickReplay>
                <To>2099-12-01T00:00:00</To>
                <TradingHoursSerializable />
                <AutoScale>true</AutoScale>
                <CenterPriceOnScale>false</CenterPriceOnScale>
                <DisplayInDataBox>true</DisplayInDataBox>
                <Label>CL AUG26</Label>
                <MaxSerialized>0</MaxSerialized>
                <MinSerialized>0</MinSerialized>
                <MonthsBack>0</MonthsBack>
                <Panel>0</Panel>
                <PriceMarker>
                  <BackgroundSerialize>DEFAULT</BackgroundSerialize>
                  <IsVisible>true</IsVisible>
                </PriceMarker>
                <ShowGlobalDrawObjects>true</ShowGlobalDrawObjects>
                <ScaleJustification>Right</ScaleJustification>
                <TradingHoursVisibility>AllSessions</TradingHoursVisibility>
                <TradingHoursBreakPenSerialize>&lt;Pen Brush="#FF2D2D2F" Thickness="1" xmlns="http://schemas.microsoft.com/winfx/2006/xaml/presentation"&gt;
  &lt;Pen.DashStyle&gt;
    &lt;DashStyle /&gt;
  &lt;/Pen.DashStyle&gt;
&lt;/Pen&gt;</TradingHoursBreakPenSerialize>
                <LongExecutionBrushSerialize>DEFAULT</LongExecutionBrushSerialize>
                <PlotExecutions>TextAndMarker</PlotExecutions>
                <MarkerSize>5</MarkerSize>
                <PositionPenLoserSerialize>DEFAULT</PositionPenLoserSerialize>
                <PositionPenWinnerSerialize>DEFAULT</PositionPenWinnerSerialize>
                <ShortExecutionBrushSerialize>DEFAULT</ShortExecutionBrushSerialize>
                <BarsSeriesId>e5040553b85348378ddac448edb70887</BarsSeriesId>
                <Id>a656a074203c44ebae8053166aa2c7ae</Id>
                <Instrument>CL AUG26</Instrument>
                <IsLinked>true</IsLinked>
                <IsPrimarySeries>true</IsPrimarySeries>
                <ZOrder>1</ZOrder>
                <WeeksBack>1</WeeksBack>
                <YearsBack>0</YearsBack>
              </BarsProperties>
              <ChartStyles>
                <ChartStyle>
                  <CandleStyle>
                    <CandleStyle xmlns:xsd="http://www.w3.org/2001/XMLSchema" xmlns:xsi="http://www.w3.org/2001/XMLSchema-instance">
                      <IsVisible>true</IsVisible>
                      <BarWidth>3</BarWidth>
                      <ChartStyleTypeSerialize>1</ChartStyleTypeSerialize>
                      <DownBrushSerialize>DEFAULT</DownBrushSerialize>
                      <UpBrushSerialize>DEFAULT</UpBrushSerialize>
                      <StrokeSerialize>DEFAULT</StrokeSerialize>
                      <Stroke2Serialize>DEFAULT</Stroke2Serialize>
                      <WickMatchesBody>true</WickMatchesBody>
                      <DojiBrushSerialize>&lt;SolidColorBrush xmlns="http://schemas.microsoft.com/winfx/2006/xaml/presentation"&gt;#FFCCCCCC&lt;/SolidColorBrush&gt;</DojiBrushSerialize>
                      <WickStyle>Solid</WickStyle>
                      <WickWidth>1</WickWidth>
                    </CandleStyle>
                  </CandleStyle>
                </ChartStyle>
              </ChartStyles>
            </BarsProperties>
          </DataSeries>
          <Strategies />
          <Indicators />
          <CrosshairType>Global</CrosshairType>
          <StayInDrawMode>False</StayInDrawMode>
          <Properties>
            <ChartControlProperties xmlns:xsd="http://www.w3.org/2001/XMLSchema" xmlns:xsi="http://www.w3.org/2001/XMLSchema-instance">
              <AlwaysOnTop>false</AlwaysOnTop>
              <AreTabsVisible>true</AreTabsVisible>
              <AllowSelectionDragging>true</AllowSelectionDragging>
              <AreDrawingToolsHidden>false</AreDrawingToolsHidden>
              <EquidistantBarSpacing>true</EquidistantBarSpacing>
              <LabelFont>
                <Bold>false</Bold>
                <FamilySerialize>Arial</FamilySerialize>
                <Italic>false</Italic>
                <Size>11</Size>
              </LabelFont>
              <BarDistance>10</BarDistance>
              <BarMarginRightUser>8</BarMarginRightUser>
              <ChartTimeFormat>TwelveHour</ChartTimeFormat>
              <ChartTraderVisibility>Collapsed</ChartTraderVisibility>
              <ShowDateRange>false</ShowDateRange>
              <ShowScrollBar>true</ShowScrollBar>
              <ShowSelectedDrawingMarkers>true</ShowSelectedDrawingMarkers>
              <SnapMode>BarAndTick</SnapMode>
              <HideIndicators>false</HideIndicators>
              <TabName>@INSTRUMENT_FULL</TabName>
              <LoadBackgroundImage>false</LoadBackgroundImage>
              <BackgroundImageStretch>Fill</BackgroundImageStretch>
              <ChartBackgroundSerialize>DEFAULT</ChartBackgroundSerialize>
              <ChartTextSerialize>DEFAULT</ChartTextSerialize>
              <CrosshairLabelBackgroundSerialize>DEFAULT</CrosshairLabelBackgroundSerialize>
              <InactivePriceMarkersBrushSerialize>DEFAULT</InactivePriceMarkersBrushSerialize>
              <SelectedMarkerBrushSerialize>DEFAULT</SelectedMarkerBrushSerialize>
              <AreHGridLinesVisible>true</AreHGridLinesVisible>
              <AreVGridLinesVisible>true</AreVGridLinesVisible>
              <AxisPenSerialize>DEFAULT</AxisPenSerialize>
              <CrosshairPen>DEFAULT</CrosshairPen>
              <CrosshairIsLocked>false</CrosshairIsLocked>
              <CrosshairCrosshairType>Global</CrosshairCrosshairType>
              <CrosshairDrawCursorOnly>false</CrosshairDrawCursorOnly>
              <GridLineHPenSerialize>DEFAULT</GridLineHPenSerialize>
              <GridLineVPenSerialize>DEFAULT</GridLineVPenSerialize>
              <PanelSplitterPenSerialize>DEFAULT</PanelSplitterPenSerialize>
              <TimeHighlighters>0</TimeHighlighters>
              <TimeHighlighter0>
                <StartTime>2025-01-01T09:00:00</StartTime>
                <EndTime>2025-01-01T17:00:00</EndTime>
                <Opacity>25</Opacity>
                <BrushSerialize>&lt;SolidColorBrush xmlns="http://schemas.microsoft.com/winfx/2006/xaml/presentation"&gt;#FF6495ED&lt;/SolidColorBrush&gt;</BrushSerialize>
              </TimeHighlighter0>
              <TimeHighlighter1>
                <StartTime>2025-01-01T09:00:00</StartTime>
                <EndTime>2025-01-01T17:00:00</EndTime>
                <Opacity>25</Opacity>
                <BrushSerialize>&lt;SolidColorBrush xmlns="http://schemas.microsoft.com/winfx/2006/xaml/presentation"&gt;#FF6495ED&lt;/SolidColorBrush&gt;</BrushSerialize>
              </TimeHighlighter1>
              <TimeHighlighter2>
                <StartTime>2025-01-01T09:00:00</StartTime>
                <EndTime>2025-01-01T17:00:00</EndTime>
                <Opacity>25</Opacity>
                <BrushSerialize>&lt;SolidColorBrush xmlns="http://schemas.microsoft.com/winfx/2006/xaml/presentation"&gt;#FF6495ED&lt;/SolidColorBrush&gt;</BrushSerialize>
              </TimeHighlighter2>
              <TimeHighlighter3>
                <StartTime>2025-01-01T09:00:00</StartTime>
                <EndTime>2025-01-01T17:00:00</EndTime>
                <Opacity>25</Opacity>
                <BrushSerialize>&lt;SolidColorBrush xmlns="http://schemas.microsoft.com/winfx/2006/xaml/presentation"&gt;#FF6495ED&lt;/SolidColorBrush&gt;</BrushSerialize>
              </TimeHighlighter3>
              <TimeHighlighter4>
                <StartTime>2025-01-01T09:00:00</StartTime>
                <EndTime>2025-01-01T17:00:00</EndTime>
                <Opacity>25</Opacity>
                <BrushSerialize>&lt;SolidColorBrush xmlns="http://schemas.microsoft.com/winfx/2006/xaml/presentation"&gt;#FF6495ED&lt;/SolidColorBrush&gt;</BrushSerialize>
              </TimeHighlighter4>
              <TimeHighlighter5>
                <StartTime>2025-01-01T09:00:00</StartTime>
                <EndTime>2025-01-01T17:00:00</EndTime>
                <Opacity>25</Opacity>
                <BrushSerialize>&lt;SolidColorBrush xmlns="http://schemas.microsoft.com/winfx/2006/xaml/presentation"&gt;#FF6495ED&lt;/SolidColorBrush&gt;</BrushSerialize>
              </TimeHighlighter5>
              <TimeHighlighter6>
                <StartTime>2025-01-01T09:00:00</StartTime>
                <EndTime>2025-01-01T17:00:00</EndTime>
                <Opacity>25</Opacity>
                <BrushSerialize>&lt;SolidColorBrush xmlns="http://schemas.microsoft.com/winfx/2006/xaml/presentation"&gt;#FF6495ED&lt;/SolidColorBrush&gt;</BrushSerialize>
              </TimeHighlighter6>
              <TimeHighlighter7>
                <StartTime>2025-01-01T09:00:00</StartTime>
                <EndTime>2025-01-01T17:00:00</EndTime>
                <Opacity>25</Opacity>
                <BrushSerialize>&lt;SolidColorBrush xmlns="http://schemas.microsoft.com/winfx/2006/xaml/presentation"&gt;#FF6495ED&lt;/SolidColorBrush&gt;</BrushSerialize>
              </TimeHighlighter7>
              <TimeHighlighter8>
                <StartTime>2025-01-01T09:00:00</StartTime>
                <EndTime>2025-01-01T17:00:00</EndTime>
                <Opacity>25</Opacity>
                <BrushSerialize>&lt;SolidColorBrush xmlns="http://schemas.microsoft.com/winfx/2006/xaml/presentation"&gt;#FF6495ED&lt;/SolidColorBrush&gt;</BrushSerialize>
              </TimeHighlighter8>
              <TimeHighlighter9>
                <StartTime>2025-01-01T09:00:00</StartTime>
                <EndTime>2025-01-01T17:00:00</EndTime>
                <Opacity>25</Opacity>
                <BrushSerialize>&lt;SolidColorBrush xmlns="http://schemas.microsoft.com/winfx/2006/xaml/presentation"&gt;#FF6495ED&lt;/SolidColorBrush&gt;</BrushSerialize>
              </TimeHighlighter9>

            </ChartControlProperties>
          </Properties>
          <ChartPanels>
            <ChartPanel>
              <Height>612</Height>
              <HoldChartTraderOrders>false</HoldChartTraderOrders>
              <IsMaximized>false</IsMaximized>
              <Right>
                <ChartScaleProperties xmlns:xsd="http://www.w3.org/2001/XMLSchema" xmlns:xsi="http://www.w3.org/2001/XMLSchema-instance">
                  <YAxisRangeType>Automatic</YAxisRangeType>
                  <AutoScaleDateRangeType>ScreenDateRange</AutoScaleDateRangeType>
                  <HorizontalGridlinesCalculation>Automatic</HorizontalGridlinesCalculation>
                  <HorizontalGridlinesIntervalType>Points</HorizontalGridlinesIntervalType>
                  <HorizontalGridlinesInterval>0</HorizontalGridlinesInterval>
                  <AutoScaleMarginType>Percent</AutoScaleMarginType>
                  <AutoScaleMarginLower>6</AutoScaleMarginLower>
                  <AutoScaleMarginUpper>6</AutoScaleMarginUpper>
                  <YAxisScalingType>Linear</YAxisScalingType>
                  <FixedScaleMaxSerialize>0</FixedScaleMaxSerialize>
                  <FixedScaleMinSerialize>0</FixedScaleMinSerialize>
                  <IsInverted>false</IsInverted>
                </ChartScaleProperties>
              </Right>
              <Left>
                <ChartScaleProperties xmlns:xsd="http://www.w3.org/2001/XMLSchema" xmlns:xsi="http://www.w3.org/2001/XMLSchema-instance">
                  <YAxisRangeType>Automatic</YAxisRangeType>
                  <AutoScaleDateRangeType>ScreenDateRange</AutoScaleDateRangeType>
                  <HorizontalGridlinesCalculation>Automatic</HorizontalGridlinesCalculation>
                  <HorizontalGridlinesIntervalType>Points</HorizontalGridlinesIntervalType>
                  <HorizontalGridlinesInterval>0</HorizontalGridlinesInterval>
                  <AutoScaleMarginType>Percent</AutoScaleMarginType>
                  <AutoScaleMarginLower>6</AutoScaleMarginLower>
                  <AutoScaleMarginUpper>6</AutoScaleMarginUpper>
                  <YAxisScalingType>Linear</YAxisScalingType>
                  <FixedScaleMaxSerialize>0</FixedScaleMaxSerialize>
                  <FixedScaleMinSerialize>0</FixedScaleMinSerialize>
                  <IsInverted>false</IsInverted>
                </ChartScaleProperties>
              </Left>
              <Overlay>
                <ChartScaleProperties xmlns:xsd="http://www.w3.org/2001/XMLSchema" xmlns:xsi="http://www.w3.org/2001/XMLSchema-instance">
                  <YAxisRangeType>Automatic</YAxisRangeType>
                  <AutoScaleDateRangeType>ScreenDateRange</AutoScaleDateRangeType>
                  <HorizontalGridlinesCalculation>Automatic</HorizontalGridlinesCalculation>
                  <HorizontalGridlinesIntervalType>Points</HorizontalGridlinesIntervalType>
                  <HorizontalGridlinesInterval>0</HorizontalGridlinesInterval>
                  <AutoScaleMarginType>Percent</AutoScaleMarginType>
                  <AutoScaleMarginLower>6</AutoScaleMarginLower>
                  <AutoScaleMarginUpper>6</AutoScaleMarginUpper>
                  <YAxisScalingType>Linear</YAxisScalingType>
                  <FixedScaleMaxSerialize>0</FixedScaleMaxSerialize>
                  <FixedScaleMinSerialize>0</FixedScaleMinSerialize>
                  <IsInverted>false</IsInverted>
                </ChartScaleProperties>
              </Overlay>
            </ChartPanel>
          </ChartPanels>
          <ChartAlerts />
          <TabName>@INSTRUMENT_FULL</TabName>
          <Type>ChartTab</Type>
        </Tab-be0949238d1340d3b8e565d0d5d9a57f>
      </TabControl>
    </Chart-611c4f7968004efcb3ec3ec19e478c73>    <Chart-360b9fa9d00249ac9173d466e6ff1260>
      <Class Assembly="NinjaTrader.Gui">NinjaTrader.Gui.Chart.Chart</Class>
      <WindowState>Normal</WindowState>
      <Location>1280;0</Location>
      <Size>1280;720</Size>
      <ZOrder>0</ZOrder>
      <Topmost>False</Topmost>
      <TraderWidth>200</TraderWidth>
      <TabControl>
        <SelectedIndex>0</SelectedIndex>
        <Tab-b3df57efacdd4550ba06e8b84d4c4efe>
          <InstrumentLink>0</InstrumentLink>
          <IntervalLink>0</IntervalLink>
          <DataSeries>
            <BarsProperties>
              <BarsProperties xmlns:xsd="http://www.w3.org/2001/XMLSchema" xmlns:xsi="http://www.w3.org/2001/XMLSchema-instance">
                <BarsPeriod>
                  <BarsPeriodTypeSerialize>1</BarsPeriodTypeSerialize>
                  <BaseBarsPeriodType>Minute</BaseBarsPeriodType>
                  <BaseBarsPeriodValue>1</BaseBarsPeriodValue>
                  <VolumetricDeltaType>BidAsk</VolumetricDeltaType>
                  <MarketDataType>Last</MarketDataType>
                  <PointAndFigurePriceType>Close</PointAndFigurePriceType>
                  <ReversalType>Tick</ReversalType>
                  <Value>5</Value>
                  <Value2>1</Value2>
                </BarsPeriod>
                <RangeType>Days</RangeType>
                <BarsBack>50</BarsBack>
                <DaysBack>60</DaysBack>
                <From>2026-01-01T00:00:00</From>
                <IsStableSession>true</IsStableSession>
                <IsTickReplay>false</IsTickReplay>
                <To>2099-12-01T00:00:00</To>
                <TradingHoursSerializable />
                <AutoScale>true</AutoScale>
                <CenterPriceOnScale>false</CenterPriceOnScale>
                <DisplayInDataBox>true</DisplayInDataBox>
                <Label>GC AUG26</Label>
                <MaxSerialized>0</MaxSerialized>
                <MinSerialized>0</MinSerialized>
                <MonthsBack>0</MonthsBack>
                <Panel>0</Panel>
                <PriceMarker>
                  <BackgroundSerialize>DEFAULT</BackgroundSerialize>
                  <IsVisible>true</IsVisible>
                </PriceMarker>
                <ShowGlobalDrawObjects>true</ShowGlobalDrawObjects>
                <ScaleJustification>Right</ScaleJustification>
                <TradingHoursVisibility>AllSessions</TradingHoursVisibility>
                <TradingHoursBreakPenSerialize>&lt;Pen Brush="#FF2D2D2F" Thickness="1" xmlns="http://schemas.microsoft.com/winfx/2006/xaml/presentation"&gt;
  &lt;Pen.DashStyle&gt;
    &lt;DashStyle /&gt;
  &lt;/Pen.DashStyle&gt;
&lt;/Pen&gt;</TradingHoursBreakPenSerialize>
                <LongExecutionBrushSerialize>DEFAULT</LongExecutionBrushSerialize>
                <PlotExecutions>TextAndMarker</PlotExecutions>
                <MarkerSize>5</MarkerSize>
                <PositionPenLoserSerialize>DEFAULT</PositionPenLoserSerialize>
                <PositionPenWinnerSerialize>DEFAULT</PositionPenWinnerSerialize>
                <ShortExecutionBrushSerialize>DEFAULT</ShortExecutionBrushSerialize>
                <BarsSeriesId>9d3fd446eb014cf18c0ff5bacb159353</BarsSeriesId>
                <Id>863e6ea1fef9452586b5578635305827</Id>
                <Instrument>GC AUG26</Instrument>
                <IsLinked>true</IsLinked>
                <IsPrimarySeries>true</IsPrimarySeries>
                <ZOrder>1</ZOrder>
                <WeeksBack>1</WeeksBack>
                <YearsBack>0</YearsBack>
              </BarsProperties>
              <ChartStyles>
                <ChartStyle>
                  <CandleStyle>
                    <CandleStyle xmlns:xsd="http://www.w3.org/2001/XMLSchema" xmlns:xsi="http://www.w3.org/2001/XMLSchema-instance">
                      <IsVisible>true</IsVisible>
                      <BarWidth>3</BarWidth>
                      <ChartStyleTypeSerialize>1</ChartStyleTypeSerialize>
                      <DownBrushSerialize>DEFAULT</DownBrushSerialize>
                      <UpBrushSerialize>DEFAULT</UpBrushSerialize>
                      <StrokeSerialize>DEFAULT</StrokeSerialize>
                      <Stroke2Serialize>DEFAULT</Stroke2Serialize>
                      <WickMatchesBody>true</WickMatchesBody>
                      <DojiBrushSerialize>&lt;SolidColorBrush xmlns="http://schemas.microsoft.com/winfx/2006/xaml/presentation"&gt;#FFCCCCCC&lt;/SolidColorBrush&gt;</DojiBrushSerialize>
                      <WickStyle>Solid</WickStyle>
                      <WickWidth>1</WickWidth>
                    </CandleStyle>
                  </CandleStyle>
                </ChartStyle>
              </ChartStyles>
            </BarsProperties>
          </DataSeries>
          <Strategies />
          <Indicators />
          <CrosshairType>Global</CrosshairType>
          <StayInDrawMode>False</StayInDrawMode>
          <Properties>
            <ChartControlProperties xmlns:xsd="http://www.w3.org/2001/XMLSchema" xmlns:xsi="http://www.w3.org/2001/XMLSchema-instance">
              <AlwaysOnTop>false</AlwaysOnTop>
              <AreTabsVisible>true</AreTabsVisible>
              <AllowSelectionDragging>true</AllowSelectionDragging>
              <AreDrawingToolsHidden>false</AreDrawingToolsHidden>
              <EquidistantBarSpacing>true</EquidistantBarSpacing>
              <LabelFont>
                <Bold>false</Bold>
                <FamilySerialize>Arial</FamilySerialize>
                <Italic>false</Italic>
                <Size>11</Size>
              </LabelFont>
              <BarDistance>10</BarDistance>
              <BarMarginRightUser>8</BarMarginRightUser>
              <ChartTimeFormat>TwelveHour</ChartTimeFormat>
              <ChartTraderVisibility>Collapsed</ChartTraderVisibility>
              <ShowDateRange>false</ShowDateRange>
              <ShowScrollBar>true</ShowScrollBar>
              <ShowSelectedDrawingMarkers>true</ShowSelectedDrawingMarkers>
              <SnapMode>BarAndTick</SnapMode>
              <HideIndicators>false</HideIndicators>
              <TabName>@INSTRUMENT_FULL</TabName>
              <LoadBackgroundImage>false</LoadBackgroundImage>
              <BackgroundImageStretch>Fill</BackgroundImageStretch>
              <ChartBackgroundSerialize>DEFAULT</ChartBackgroundSerialize>
              <ChartTextSerialize>DEFAULT</ChartTextSerialize>
              <CrosshairLabelBackgroundSerialize>DEFAULT</CrosshairLabelBackgroundSerialize>
              <InactivePriceMarkersBrushSerialize>DEFAULT</InactivePriceMarkersBrushSerialize>
              <SelectedMarkerBrushSerialize>DEFAULT</SelectedMarkerBrushSerialize>
              <AreHGridLinesVisible>true</AreHGridLinesVisible>
              <AreVGridLinesVisible>true</AreVGridLinesVisible>
              <AxisPenSerialize>DEFAULT</AxisPenSerialize>
              <CrosshairPen>DEFAULT</CrosshairPen>
              <CrosshairIsLocked>false</CrosshairIsLocked>
              <CrosshairCrosshairType>Global</CrosshairCrosshairType>
              <CrosshairDrawCursorOnly>false</CrosshairDrawCursorOnly>
              <GridLineHPenSerialize>DEFAULT</GridLineHPenSerialize>
              <GridLineVPenSerialize>DEFAULT</GridLineVPenSerialize>
              <PanelSplitterPenSerialize>DEFAULT</PanelSplitterPenSerialize>
              <TimeHighlighters>0</TimeHighlighters>
              <TimeHighlighter0>
                <StartTime>2025-01-01T09:00:00</StartTime>
                <EndTime>2025-01-01T17:00:00</EndTime>
                <Opacity>25</Opacity>
                <BrushSerialize>&lt;SolidColorBrush xmlns="http://schemas.microsoft.com/winfx/2006/xaml/presentation"&gt;#FF6495ED&lt;/SolidColorBrush&gt;</BrushSerialize>
              </TimeHighlighter0>
              <TimeHighlighter1>
                <StartTime>2025-01-01T09:00:00</StartTime>
                <EndTime>2025-01-01T17:00:00</EndTime>
                <Opacity>25</Opacity>
                <BrushSerialize>&lt;SolidColorBrush xmlns="http://schemas.microsoft.com/winfx/2006/xaml/presentation"&gt;#FF6495ED&lt;/SolidColorBrush&gt;</BrushSerialize>
              </TimeHighlighter1>
              <TimeHighlighter2>
                <StartTime>2025-01-01T09:00:00</StartTime>
                <EndTime>2025-01-01T17:00:00</EndTime>
                <Opacity>25</Opacity>
                <BrushSerialize>&lt;SolidColorBrush xmlns="http://schemas.microsoft.com/winfx/2006/xaml/presentation"&gt;#FF6495ED&lt;/SolidColorBrush&gt;</BrushSerialize>
              </TimeHighlighter2>
              <TimeHighlighter3>
                <StartTime>2025-01-01T09:00:00</StartTime>
                <EndTime>2025-01-01T17:00:00</EndTime>
                <Opacity>25</Opacity>
                <BrushSerialize>&lt;SolidColorBrush xmlns="http://schemas.microsoft.com/winfx/2006/xaml/presentation"&gt;#FF6495ED&lt;/SolidColorBrush&gt;</BrushSerialize>
              </TimeHighlighter3>
              <TimeHighlighter4>
                <StartTime>2025-01-01T09:00:00</StartTime>
                <EndTime>2025-01-01T17:00:00</EndTime>
                <Opacity>25</Opacity>
                <BrushSerialize>&lt;SolidColorBrush xmlns="http://schemas.microsoft.com/winfx/2006/xaml/presentation"&gt;#FF6495ED&lt;/SolidColorBrush&gt;</BrushSerialize>
              </TimeHighlighter4>
              <TimeHighlighter5>
                <StartTime>2025-01-01T09:00:00</StartTime>
                <EndTime>2025-01-01T17:00:00</EndTime>
                <Opacity>25</Opacity>
                <BrushSerialize>&lt;SolidColorBrush xmlns="http://schemas.microsoft.com/winfx/2006/xaml/presentation"&gt;#FF6495ED&lt;/SolidColorBrush&gt;</BrushSerialize>
              </TimeHighlighter5>
              <TimeHighlighter6>
                <StartTime>2025-01-01T09:00:00</StartTime>
                <EndTime>2025-01-01T17:00:00</EndTime>
                <Opacity>25</Opacity>
                <BrushSerialize>&lt;SolidColorBrush xmlns="http://schemas.microsoft.com/winfx/2006/xaml/presentation"&gt;#FF6495ED&lt;/SolidColorBrush&gt;</BrushSerialize>
              </TimeHighlighter6>
              <TimeHighlighter7>
                <StartTime>2025-01-01T09:00:00</StartTime>
                <EndTime>2025-01-01T17:00:00</EndTime>
                <Opacity>25</Opacity>
                <BrushSerialize>&lt;SolidColorBrush xmlns="http://schemas.microsoft.com/winfx/2006/xaml/presentation"&gt;#FF6495ED&lt;/SolidColorBrush&gt;</BrushSerialize>
              </TimeHighlighter7>
              <TimeHighlighter8>
                <StartTime>2025-01-01T09:00:00</StartTime>
                <EndTime>2025-01-01T17:00:00</EndTime>
                <Opacity>25</Opacity>
                <BrushSerialize>&lt;SolidColorBrush xmlns="http://schemas.microsoft.com/winfx/2006/xaml/presentation"&gt;#FF6495ED&lt;/SolidColorBrush&gt;</BrushSerialize>
              </TimeHighlighter8>
              <TimeHighlighter9>
                <StartTime>2025-01-01T09:00:00</StartTime>
                <EndTime>2025-01-01T17:00:00</EndTime>
                <Opacity>25</Opacity>
                <BrushSerialize>&lt;SolidColorBrush xmlns="http://schemas.microsoft.com/winfx/2006/xaml/presentation"&gt;#FF6495ED&lt;/SolidColorBrush&gt;</BrushSerialize>
              </TimeHighlighter9>

            </ChartControlProperties>
          </Properties>
          <ChartPanels>
            <ChartPanel>
              <Height>612</Height>
              <HoldChartTraderOrders>false</HoldChartTraderOrders>
              <IsMaximized>false</IsMaximized>
              <Right>
                <ChartScaleProperties xmlns:xsd="http://www.w3.org/2001/XMLSchema" xmlns:xsi="http://www.w3.org/2001/XMLSchema-instance">
                  <YAxisRangeType>Automatic</YAxisRangeType>
                  <AutoScaleDateRangeType>ScreenDateRange</AutoScaleDateRangeType>
                  <HorizontalGridlinesCalculation>Automatic</HorizontalGridlinesCalculation>
                  <HorizontalGridlinesIntervalType>Points</HorizontalGridlinesIntervalType>
                  <HorizontalGridlinesInterval>0</HorizontalGridlinesInterval>
                  <AutoScaleMarginType>Percent</AutoScaleMarginType>
                  <AutoScaleMarginLower>6</AutoScaleMarginLower>
                  <AutoScaleMarginUpper>6</AutoScaleMarginUpper>
                  <YAxisScalingType>Linear</YAxisScalingType>
                  <FixedScaleMaxSerialize>0</FixedScaleMaxSerialize>
                  <FixedScaleMinSerialize>0</FixedScaleMinSerialize>
                  <IsInverted>false</IsInverted>
                </ChartScaleProperties>
              </Right>
              <Left>
                <ChartScaleProperties xmlns:xsd="http://www.w3.org/2001/XMLSchema" xmlns:xsi="http://www.w3.org/2001/XMLSchema-instance">
                  <YAxisRangeType>Automatic</YAxisRangeType>
                  <AutoScaleDateRangeType>ScreenDateRange</AutoScaleDateRangeType>
                  <HorizontalGridlinesCalculation>Automatic</HorizontalGridlinesCalculation>
                  <HorizontalGridlinesIntervalType>Points</HorizontalGridlinesIntervalType>
                  <HorizontalGridlinesInterval>0</HorizontalGridlinesInterval>
                  <AutoScaleMarginType>Percent</AutoScaleMarginType>
                  <AutoScaleMarginLower>6</AutoScaleMarginLower>
                  <AutoScaleMarginUpper>6</AutoScaleMarginUpper>
                  <YAxisScalingType>Linear</YAxisScalingType>
                  <FixedScaleMaxSerialize>0</FixedScaleMaxSerialize>
                  <FixedScaleMinSerialize>0</FixedScaleMinSerialize>
                  <IsInverted>false</IsInverted>
                </ChartScaleProperties>
              </Left>
              <Overlay>
                <ChartScaleProperties xmlns:xsd="http://www.w3.org/2001/XMLSchema" xmlns:xsi="http://www.w3.org/2001/XMLSchema-instance">
                  <YAxisRangeType>Automatic</YAxisRangeType>
                  <AutoScaleDateRangeType>ScreenDateRange</AutoScaleDateRangeType>
                  <HorizontalGridlinesCalculation>Automatic</HorizontalGridlinesCalculation>
                  <HorizontalGridlinesIntervalType>Points</HorizontalGridlinesIntervalType>
                  <HorizontalGridlinesInterval>0</HorizontalGridlinesInterval>
                  <AutoScaleMarginType>Percent</AutoScaleMarginType>
                  <AutoScaleMarginLower>6</AutoScaleMarginLower>
                  <AutoScaleMarginUpper>6</AutoScaleMarginUpper>
                  <YAxisScalingType>Linear</YAxisScalingType>
                  <FixedScaleMaxSerialize>0</FixedScaleMaxSerialize>
                  <FixedScaleMinSerialize>0</FixedScaleMinSerialize>
                  <IsInverted>false</IsInverted>
                </ChartScaleProperties>
              </Overlay>
            </ChartPanel>
          </ChartPanels>
          <ChartAlerts />
          <TabName>@INSTRUMENT_FULL</TabName>
          <Type>ChartTab</Type>
        </Tab-b3df57efacdd4550ba06e8b84d4c4efe>
      </TabControl>
    </Chart-360b9fa9d00249ac9173d466e6ff1260>    <Chart-5a2fdc590da54f939815e5ee69053567>
      <Class Assembly="NinjaTrader.Gui">NinjaTrader.Gui.Chart.Chart</Class>
      <WindowState>Normal</WindowState>
      <Location>0;720</Location>
      <Size>1280;720</Size>
      <ZOrder>0</ZOrder>
      <Topmost>False</Topmost>
      <TraderWidth>200</TraderWidth>
      <TabControl>
        <SelectedIndex>0</SelectedIndex>
        <Tab-7ad0974428364dbf99b7b59788b9fd7d>
          <InstrumentLink>0</InstrumentLink>
          <IntervalLink>0</IntervalLink>
          <DataSeries>
            <BarsProperties>
              <BarsProperties xmlns:xsd="http://www.w3.org/2001/XMLSchema" xmlns:xsi="http://www.w3.org/2001/XMLSchema-instance">
                <BarsPeriod>
                  <BarsPeriodTypeSerialize>1</BarsPeriodTypeSerialize>
                  <BaseBarsPeriodType>Minute</BaseBarsPeriodType>
                  <BaseBarsPeriodValue>1</BaseBarsPeriodValue>
                  <VolumetricDeltaType>BidAsk</VolumetricDeltaType>
                  <MarketDataType>Last</MarketDataType>
                  <PointAndFigurePriceType>Close</PointAndFigurePriceType>
                  <ReversalType>Tick</ReversalType>
                  <Value>15</Value>
                  <Value2>1</Value2>
                </BarsPeriod>
                <RangeType>Days</RangeType>
                <BarsBack>50</BarsBack>
                <DaysBack>60</DaysBack>
                <From>2026-01-01T00:00:00</From>
                <IsStableSession>true</IsStableSession>
                <IsTickReplay>false</IsTickReplay>
                <To>2099-12-01T00:00:00</To>
                <TradingHoursSerializable />
                <AutoScale>true</AutoScale>
                <CenterPriceOnScale>false</CenterPriceOnScale>
                <DisplayInDataBox>true</DisplayInDataBox>
                <Label>CL AUG26</Label>
                <MaxSerialized>0</MaxSerialized>
                <MinSerialized>0</MinSerialized>
                <MonthsBack>0</MonthsBack>
                <Panel>0</Panel>
                <PriceMarker>
                  <BackgroundSerialize>DEFAULT</BackgroundSerialize>
                  <IsVisible>true</IsVisible>
                </PriceMarker>
                <ShowGlobalDrawObjects>true</ShowGlobalDrawObjects>
                <ScaleJustification>Right</ScaleJustification>
                <TradingHoursVisibility>AllSessions</TradingHoursVisibility>
                <TradingHoursBreakPenSerialize>&lt;Pen Brush="#FF2D2D2F" Thickness="1" xmlns="http://schemas.microsoft.com/winfx/2006/xaml/presentation"&gt;
  &lt;Pen.DashStyle&gt;
    &lt;DashStyle /&gt;
  &lt;/Pen.DashStyle&gt;
&lt;/Pen&gt;</TradingHoursBreakPenSerialize>
                <LongExecutionBrushSerialize>DEFAULT</LongExecutionBrushSerialize>
                <PlotExecutions>TextAndMarker</PlotExecutions>
                <MarkerSize>5</MarkerSize>
                <PositionPenLoserSerialize>DEFAULT</PositionPenLoserSerialize>
                <PositionPenWinnerSerialize>DEFAULT</PositionPenWinnerSerialize>
                <ShortExecutionBrushSerialize>DEFAULT</ShortExecutionBrushSerialize>
                <BarsSeriesId>1e98525226ef470795ceeb2770ae5a89</BarsSeriesId>
                <Id>8ec2b11775b74d16b0b7ed9844273561</Id>
                <Instrument>CL AUG26</Instrument>
                <IsLinked>true</IsLinked>
                <IsPrimarySeries>true</IsPrimarySeries>
                <ZOrder>1</ZOrder>
                <WeeksBack>1</WeeksBack>
                <YearsBack>0</YearsBack>
              </BarsProperties>
              <ChartStyles>
                <ChartStyle>
                  <CandleStyle>
                    <CandleStyle xmlns:xsd="http://www.w3.org/2001/XMLSchema" xmlns:xsi="http://www.w3.org/2001/XMLSchema-instance">
                      <IsVisible>true</IsVisible>
                      <BarWidth>3</BarWidth>
                      <ChartStyleTypeSerialize>1</ChartStyleTypeSerialize>
                      <DownBrushSerialize>DEFAULT</DownBrushSerialize>
                      <UpBrushSerialize>DEFAULT</UpBrushSerialize>
                      <StrokeSerialize>DEFAULT</StrokeSerialize>
                      <Stroke2Serialize>DEFAULT</Stroke2Serialize>
                      <WickMatchesBody>true</WickMatchesBody>
                      <DojiBrushSerialize>&lt;SolidColorBrush xmlns="http://schemas.microsoft.com/winfx/2006/xaml/presentation"&gt;#FFCCCCCC&lt;/SolidColorBrush&gt;</DojiBrushSerialize>
                      <WickStyle>Solid</WickStyle>
                      <WickWidth>1</WickWidth>
                    </CandleStyle>
                  </CandleStyle>
                </ChartStyle>
              </ChartStyles>
            </BarsProperties>
          </DataSeries>
          <Strategies />
          <Indicators />
          <CrosshairType>Global</CrosshairType>
          <StayInDrawMode>False</StayInDrawMode>
          <Properties>
            <ChartControlProperties xmlns:xsd="http://www.w3.org/2001/XMLSchema" xmlns:xsi="http://www.w3.org/2001/XMLSchema-instance">
              <AlwaysOnTop>false</AlwaysOnTop>
              <AreTabsVisible>true</AreTabsVisible>
              <AllowSelectionDragging>true</AllowSelectionDragging>
              <AreDrawingToolsHidden>false</AreDrawingToolsHidden>
              <EquidistantBarSpacing>true</EquidistantBarSpacing>
              <LabelFont>
                <Bold>false</Bold>
                <FamilySerialize>Arial</FamilySerialize>
                <Italic>false</Italic>
                <Size>11</Size>
              </LabelFont>
              <BarDistance>10</BarDistance>
              <BarMarginRightUser>8</BarMarginRightUser>
              <ChartTimeFormat>TwelveHour</ChartTimeFormat>
              <ChartTraderVisibility>Collapsed</ChartTraderVisibility>
              <ShowDateRange>false</ShowDateRange>
              <ShowScrollBar>true</ShowScrollBar>
              <ShowSelectedDrawingMarkers>true</ShowSelectedDrawingMarkers>
              <SnapMode>BarAndTick</SnapMode>
              <HideIndicators>false</HideIndicators>
              <TabName>@INSTRUMENT_FULL</TabName>
              <LoadBackgroundImage>false</LoadBackgroundImage>
              <BackgroundImageStretch>Fill</BackgroundImageStretch>
              <ChartBackgroundSerialize>DEFAULT</ChartBackgroundSerialize>
              <ChartTextSerialize>DEFAULT</ChartTextSerialize>
              <CrosshairLabelBackgroundSerialize>DEFAULT</CrosshairLabelBackgroundSerialize>
              <InactivePriceMarkersBrushSerialize>DEFAULT</InactivePriceMarkersBrushSerialize>
              <SelectedMarkerBrushSerialize>DEFAULT</SelectedMarkerBrushSerialize>
              <AreHGridLinesVisible>true</AreHGridLinesVisible>
              <AreVGridLinesVisible>true</AreVGridLinesVisible>
              <AxisPenSerialize>DEFAULT</AxisPenSerialize>
              <CrosshairPen>DEFAULT</CrosshairPen>
              <CrosshairIsLocked>false</CrosshairIsLocked>
              <CrosshairCrosshairType>Global</CrosshairCrosshairType>
              <CrosshairDrawCursorOnly>false</CrosshairDrawCursorOnly>
              <GridLineHPenSerialize>DEFAULT</GridLineHPenSerialize>
              <GridLineVPenSerialize>DEFAULT</GridLineVPenSerialize>
              <PanelSplitterPenSerialize>DEFAULT</PanelSplitterPenSerialize>
              <TimeHighlighters>0</TimeHighlighters>
              <TimeHighlighter0>
                <StartTime>2025-01-01T09:00:00</StartTime>
                <EndTime>2025-01-01T17:00:00</EndTime>
                <Opacity>25</Opacity>
                <BrushSerialize>&lt;SolidColorBrush xmlns="http://schemas.microsoft.com/winfx/2006/xaml/presentation"&gt;#FF6495ED&lt;/SolidColorBrush&gt;</BrushSerialize>
              </TimeHighlighter0>
              <TimeHighlighter1>
                <StartTime>2025-01-01T09:00:00</StartTime>
                <EndTime>2025-01-01T17:00:00</EndTime>
                <Opacity>25</Opacity>
                <BrushSerialize>&lt;SolidColorBrush xmlns="http://schemas.microsoft.com/winfx/2006/xaml/presentation"&gt;#FF6495ED&lt;/SolidColorBrush&gt;</BrushSerialize>
              </TimeHighlighter1>
              <TimeHighlighter2>
                <StartTime>2025-01-01T09:00:00</StartTime>
                <EndTime>2025-01-01T17:00:00</EndTime>
                <Opacity>25</Opacity>
                <BrushSerialize>&lt;SolidColorBrush xmlns="http://schemas.microsoft.com/winfx/2006/xaml/presentation"&gt;#FF6495ED&lt;/SolidColorBrush&gt;</BrushSerialize>
              </TimeHighlighter2>
              <TimeHighlighter3>
                <StartTime>2025-01-01T09:00:00</StartTime>
                <EndTime>2025-01-01T17:00:00</EndTime>
                <Opacity>25</Opacity>
                <BrushSerialize>&lt;SolidColorBrush xmlns="http://schemas.microsoft.com/winfx/2006/xaml/presentation"&gt;#FF6495ED&lt;/SolidColorBrush&gt;</BrushSerialize>
              </TimeHighlighter3>
              <TimeHighlighter4>
                <StartTime>2025-01-01T09:00:00</StartTime>
                <EndTime>2025-01-01T17:00:00</EndTime>
                <Opacity>25</Opacity>
                <BrushSerialize>&lt;SolidColorBrush xmlns="http://schemas.microsoft.com/winfx/2006/xaml/presentation"&gt;#FF6495ED&lt;/SolidColorBrush&gt;</BrushSerialize>
              </TimeHighlighter4>
              <TimeHighlighter5>
                <StartTime>2025-01-01T09:00:00</StartTime>
                <EndTime>2025-01-01T17:00:00</EndTime>
                <Opacity>25</Opacity>
                <BrushSerialize>&lt;SolidColorBrush xmlns="http://schemas.microsoft.com/winfx/2006/xaml/presentation"&gt;#FF6495ED&lt;/SolidColorBrush&gt;</BrushSerialize>
              </TimeHighlighter5>
              <TimeHighlighter6>
                <StartTime>2025-01-01T09:00:00</StartTime>
                <EndTime>2025-01-01T17:00:00</EndTime>
                <Opacity>25</Opacity>
                <BrushSerialize>&lt;SolidColorBrush xmlns="http://schemas.microsoft.com/winfx/2006/xaml/presentation"&gt;#FF6495ED&lt;/SolidColorBrush&gt;</BrushSerialize>
              </TimeHighlighter6>
              <TimeHighlighter7>
                <StartTime>2025-01-01T09:00:00</StartTime>
                <EndTime>2025-01-01T17:00:00</EndTime>
                <Opacity>25</Opacity>
                <BrushSerialize>&lt;SolidColorBrush xmlns="http://schemas.microsoft.com/winfx/2006/xaml/presentation"&gt;#FF6495ED&lt;/SolidColorBrush&gt;</BrushSerialize>
              </TimeHighlighter7>
              <TimeHighlighter8>
                <StartTime>2025-01-01T09:00:00</StartTime>
                <EndTime>2025-01-01T17:00:00</EndTime>
                <Opacity>25</Opacity>
                <BrushSerialize>&lt;SolidColorBrush xmlns="http://schemas.microsoft.com/winfx/2006/xaml/presentation"&gt;#FF6495ED&lt;/SolidColorBrush&gt;</BrushSerialize>
              </TimeHighlighter8>
              <TimeHighlighter9>
                <StartTime>2025-01-01T09:00:00</StartTime>
                <EndTime>2025-01-01T17:00:00</EndTime>
                <Opacity>25</Opacity>
                <BrushSerialize>&lt;SolidColorBrush xmlns="http://schemas.microsoft.com/winfx/2006/xaml/presentation"&gt;#FF6495ED&lt;/SolidColorBrush&gt;</BrushSerialize>
              </TimeHighlighter9>

            </ChartControlProperties>
          </Properties>
          <ChartPanels>
            <ChartPanel>
              <Height>612</Height>
              <HoldChartTraderOrders>false</HoldChartTraderOrders>
              <IsMaximized>false</IsMaximized>
              <Right>
                <ChartScaleProperties xmlns:xsd="http://www.w3.org/2001/XMLSchema" xmlns:xsi="http://www.w3.org/2001/XMLSchema-instance">
                  <YAxisRangeType>Automatic</YAxisRangeType>
                  <AutoScaleDateRangeType>ScreenDateRange</AutoScaleDateRangeType>
                  <HorizontalGridlinesCalculation>Automatic</HorizontalGridlinesCalculation>
                  <HorizontalGridlinesIntervalType>Points</HorizontalGridlinesIntervalType>
                  <HorizontalGridlinesInterval>0</HorizontalGridlinesInterval>
                  <AutoScaleMarginType>Percent</AutoScaleMarginType>
                  <AutoScaleMarginLower>6</AutoScaleMarginLower>
                  <AutoScaleMarginUpper>6</AutoScaleMarginUpper>
                  <YAxisScalingType>Linear</YAxisScalingType>
                  <FixedScaleMaxSerialize>0</FixedScaleMaxSerialize>
                  <FixedScaleMinSerialize>0</FixedScaleMinSerialize>
                  <IsInverted>false</IsInverted>
                </ChartScaleProperties>
              </Right>
              <Left>
                <ChartScaleProperties xmlns:xsd="http://www.w3.org/2001/XMLSchema" xmlns:xsi="http://www.w3.org/2001/XMLSchema-instance">
                  <YAxisRangeType>Automatic</YAxisRangeType>
                  <AutoScaleDateRangeType>ScreenDateRange</AutoScaleDateRangeType>
                  <HorizontalGridlinesCalculation>Automatic</HorizontalGridlinesCalculation>
                  <HorizontalGridlinesIntervalType>Points</HorizontalGridlinesIntervalType>
                  <HorizontalGridlinesInterval>0</HorizontalGridlinesInterval>
                  <AutoScaleMarginType>Percent</AutoScaleMarginType>
                  <AutoScaleMarginLower>6</AutoScaleMarginLower>
                  <AutoScaleMarginUpper>6</AutoScaleMarginUpper>
                  <YAxisScalingType>Linear</YAxisScalingType>
                  <FixedScaleMaxSerialize>0</FixedScaleMaxSerialize>
                  <FixedScaleMinSerialize>0</FixedScaleMinSerialize>
                  <IsInverted>false</IsInverted>
                </ChartScaleProperties>
              </Left>
              <Overlay>
                <ChartScaleProperties xmlns:xsd="http://www.w3.org/2001/XMLSchema" xmlns:xsi="http://www.w3.org/2001/XMLSchema-instance">
                  <YAxisRangeType>Automatic</YAxisRangeType>
                  <AutoScaleDateRangeType>ScreenDateRange</AutoScaleDateRangeType>
                  <HorizontalGridlinesCalculation>Automatic</HorizontalGridlinesCalculation>
                  <HorizontalGridlinesIntervalType>Points</HorizontalGridlinesIntervalType>
                  <HorizontalGridlinesInterval>0</HorizontalGridlinesInterval>
                  <AutoScaleMarginType>Percent</AutoScaleMarginType>
                  <AutoScaleMarginLower>6</AutoScaleMarginLower>
                  <AutoScaleMarginUpper>6</AutoScaleMarginUpper>
                  <YAxisScalingType>Linear</YAxisScalingType>
                  <FixedScaleMaxSerialize>0</FixedScaleMaxSerialize>
                  <FixedScaleMinSerialize>0</FixedScaleMinSerialize>
                  <IsInverted>false</IsInverted>
                </ChartScaleProperties>
              </Overlay>
            </ChartPanel>
          </ChartPanels>
          <ChartAlerts />
          <TabName>@INSTRUMENT_FULL</TabName>
          <Type>ChartTab</Type>
        </Tab-7ad0974428364dbf99b7b59788b9fd7d>
      </TabControl>
    </Chart-5a2fdc590da54f939815e5ee69053567>    <Chart-c5effcc8dc3a46e8bb49271b6bb2d6fd>
      <Class Assembly="NinjaTrader.Gui">NinjaTrader.Gui.Chart.Chart</Class>
      <WindowState>Normal</WindowState>
      <Location>1280;720</Location>
      <Size>1280;720</Size>
      <ZOrder>0</ZOrder>
      <Topmost>False</Topmost>
      <TraderWidth>200</TraderWidth>
      <TabControl>
        <SelectedIndex>0</SelectedIndex>
        <Tab-e85edf1a4ed94b8bacd18201a3905566>
          <InstrumentLink>0</InstrumentLink>
          <IntervalLink>0</IntervalLink>
          <DataSeries>
            <BarsProperties>
              <BarsProperties xmlns:xsd="http://www.w3.org/2001/XMLSchema" xmlns:xsi="http://www.w3.org/2001/XMLSchema-instance">
                <BarsPeriod>
                  <BarsPeriodTypeSerialize>1</BarsPeriodTypeSerialize>
                  <BaseBarsPeriodType>Minute</BaseBarsPeriodType>
                  <BaseBarsPeriodValue>1</BaseBarsPeriodValue>
                  <VolumetricDeltaType>BidAsk</VolumetricDeltaType>
                  <MarketDataType>Last</MarketDataType>
                  <PointAndFigurePriceType>Close</PointAndFigurePriceType>
                  <ReversalType>Tick</ReversalType>
                  <Value>15</Value>
                  <Value2>1</Value2>
                </BarsPeriod>
                <RangeType>Days</RangeType>
                <BarsBack>50</BarsBack>
                <DaysBack>60</DaysBack>
                <From>2026-01-01T00:00:00</From>
                <IsStableSession>true</IsStableSession>
                <IsTickReplay>false</IsTickReplay>
                <To>2099-12-01T00:00:00</To>
                <TradingHoursSerializable />
                <AutoScale>true</AutoScale>
                <CenterPriceOnScale>false</CenterPriceOnScale>
                <DisplayInDataBox>true</DisplayInDataBox>
                <Label>GC AUG26</Label>
                <MaxSerialized>0</MaxSerialized>
                <MinSerialized>0</MinSerialized>
                <MonthsBack>0</MonthsBack>
                <Panel>0</Panel>
                <PriceMarker>
                  <BackgroundSerialize>DEFAULT</BackgroundSerialize>
                  <IsVisible>true</IsVisible>
                </PriceMarker>
                <ShowGlobalDrawObjects>true</ShowGlobalDrawObjects>
                <ScaleJustification>Right</ScaleJustification>
                <TradingHoursVisibility>AllSessions</TradingHoursVisibility>
                <TradingHoursBreakPenSerialize>&lt;Pen Brush="#FF2D2D2F" Thickness="1" xmlns="http://schemas.microsoft.com/winfx/2006/xaml/presentation"&gt;
  &lt;Pen.DashStyle&gt;
    &lt;DashStyle /&gt;
  &lt;/Pen.DashStyle&gt;
&lt;/Pen&gt;</TradingHoursBreakPenSerialize>
                <LongExecutionBrushSerialize>DEFAULT</LongExecutionBrushSerialize>
                <PlotExecutions>TextAndMarker</PlotExecutions>
                <MarkerSize>5</MarkerSize>
                <PositionPenLoserSerialize>DEFAULT</PositionPenLoserSerialize>
                <PositionPenWinnerSerialize>DEFAULT</PositionPenWinnerSerialize>
                <ShortExecutionBrushSerialize>DEFAULT</ShortExecutionBrushSerialize>
                <BarsSeriesId>0255c35c98eb41eb9f5b958b357d4d56</BarsSeriesId>
                <Id>b237b739cccb4cd79c38fe875adc1263</Id>
                <Instrument>GC AUG26</Instrument>
                <IsLinked>true</IsLinked>
                <IsPrimarySeries>true</IsPrimarySeries>
                <ZOrder>1</ZOrder>
                <WeeksBack>1</WeeksBack>
                <YearsBack>0</YearsBack>
              </BarsProperties>
              <ChartStyles>
                <ChartStyle>
                  <CandleStyle>
                    <CandleStyle xmlns:xsd="http://www.w3.org/2001/XMLSchema" xmlns:xsi="http://www.w3.org/2001/XMLSchema-instance">
                      <IsVisible>true</IsVisible>
                      <BarWidth>3</BarWidth>
                      <ChartStyleTypeSerialize>1</ChartStyleTypeSerialize>
                      <DownBrushSerialize>DEFAULT</DownBrushSerialize>
                      <UpBrushSerialize>DEFAULT</UpBrushSerialize>
                      <StrokeSerialize>DEFAULT</StrokeSerialize>
                      <Stroke2Serialize>DEFAULT</Stroke2Serialize>
                      <WickMatchesBody>true</WickMatchesBody>
                      <DojiBrushSerialize>&lt;SolidColorBrush xmlns="http://schemas.microsoft.com/winfx/2006/xaml/presentation"&gt;#FFCCCCCC&lt;/SolidColorBrush&gt;</DojiBrushSerialize>
                      <WickStyle>Solid</WickStyle>
                      <WickWidth>1</WickWidth>
                    </CandleStyle>
                  </CandleStyle>
                </ChartStyle>
              </ChartStyles>
            </BarsProperties>
          </DataSeries>
          <Strategies />
          <Indicators />
          <CrosshairType>Global</CrosshairType>
          <StayInDrawMode>False</StayInDrawMode>
          <Properties>
            <ChartControlProperties xmlns:xsd="http://www.w3.org/2001/XMLSchema" xmlns:xsi="http://www.w3.org/2001/XMLSchema-instance">
              <AlwaysOnTop>false</AlwaysOnTop>
              <AreTabsVisible>true</AreTabsVisible>
              <AllowSelectionDragging>true</AllowSelectionDragging>
              <AreDrawingToolsHidden>false</AreDrawingToolsHidden>
              <EquidistantBarSpacing>true</EquidistantBarSpacing>
              <LabelFont>
                <Bold>false</Bold>
                <FamilySerialize>Arial</FamilySerialize>
                <Italic>false</Italic>
                <Size>11</Size>
              </LabelFont>
              <BarDistance>10</BarDistance>
              <BarMarginRightUser>8</BarMarginRightUser>
              <ChartTimeFormat>TwelveHour</ChartTimeFormat>
              <ChartTraderVisibility>Collapsed</ChartTraderVisibility>
              <ShowDateRange>false</ShowDateRange>
              <ShowScrollBar>true</ShowScrollBar>
              <ShowSelectedDrawingMarkers>true</ShowSelectedDrawingMarkers>
              <SnapMode>BarAndTick</SnapMode>
              <HideIndicators>false</HideIndicators>
              <TabName>@INSTRUMENT_FULL</TabName>
              <LoadBackgroundImage>false</LoadBackgroundImage>
              <BackgroundImageStretch>Fill</BackgroundImageStretch>
              <ChartBackgroundSerialize>DEFAULT</ChartBackgroundSerialize>
              <ChartTextSerialize>DEFAULT</ChartTextSerialize>
              <CrosshairLabelBackgroundSerialize>DEFAULT</CrosshairLabelBackgroundSerialize>
              <InactivePriceMarkersBrushSerialize>DEFAULT</InactivePriceMarkersBrushSerialize>
              <SelectedMarkerBrushSerialize>DEFAULT</SelectedMarkerBrushSerialize>
              <AreHGridLinesVisible>true</AreHGridLinesVisible>
              <AreVGridLinesVisible>true</AreVGridLinesVisible>
              <AxisPenSerialize>DEFAULT</AxisPenSerialize>
              <CrosshairPen>DEFAULT</CrosshairPen>
              <CrosshairIsLocked>false</CrosshairIsLocked>
              <CrosshairCrosshairType>Global</CrosshairCrosshairType>
              <CrosshairDrawCursorOnly>false</CrosshairDrawCursorOnly>
              <GridLineHPenSerialize>DEFAULT</GridLineHPenSerialize>
              <GridLineVPenSerialize>DEFAULT</GridLineVPenSerialize>
              <PanelSplitterPenSerialize>DEFAULT</PanelSplitterPenSerialize>
              <TimeHighlighters>0</TimeHighlighters>
              <TimeHighlighter0>
                <StartTime>2025-01-01T09:00:00</StartTime>
                <EndTime>2025-01-01T17:00:00</EndTime>
                <Opacity>25</Opacity>
                <BrushSerialize>&lt;SolidColorBrush xmlns="http://schemas.microsoft.com/winfx/2006/xaml/presentation"&gt;#FF6495ED&lt;/SolidColorBrush&gt;</BrushSerialize>
              </TimeHighlighter0>
              <TimeHighlighter1>
                <StartTime>2025-01-01T09:00:00</StartTime>
                <EndTime>2025-01-01T17:00:00</EndTime>
                <Opacity>25</Opacity>
                <BrushSerialize>&lt;SolidColorBrush xmlns="http://schemas.microsoft.com/winfx/2006/xaml/presentation"&gt;#FF6495ED&lt;/SolidColorBrush&gt;</BrushSerialize>
              </TimeHighlighter1>
              <TimeHighlighter2>
                <StartTime>2025-01-01T09:00:00</StartTime>
                <EndTime>2025-01-01T17:00:00</EndTime>
                <Opacity>25</Opacity>
                <BrushSerialize>&lt;SolidColorBrush xmlns="http://schemas.microsoft.com/winfx/2006/xaml/presentation"&gt;#FF6495ED&lt;/SolidColorBrush&gt;</BrushSerialize>
              </TimeHighlighter2>
              <TimeHighlighter3>
                <StartTime>2025-01-01T09:00:00</StartTime>
                <EndTime>2025-01-01T17:00:00</EndTime>
                <Opacity>25</Opacity>
                <BrushSerialize>&lt;SolidColorBrush xmlns="http://schemas.microsoft.com/winfx/2006/xaml/presentation"&gt;#FF6495ED&lt;/SolidColorBrush&gt;</BrushSerialize>
              </TimeHighlighter3>
              <TimeHighlighter4>
                <StartTime>2025-01-01T09:00:00</StartTime>
                <EndTime>2025-01-01T17:00:00</EndTime>
                <Opacity>25</Opacity>
                <BrushSerialize>&lt;SolidColorBrush xmlns="http://schemas.microsoft.com/winfx/2006/xaml/presentation"&gt;#FF6495ED&lt;/SolidColorBrush&gt;</BrushSerialize>
              </TimeHighlighter4>
              <TimeHighlighter5>
                <StartTime>2025-01-01T09:00:00</StartTime>
                <EndTime>2025-01-01T17:00:00</EndTime>
                <Opacity>25</Opacity>
                <BrushSerialize>&lt;SolidColorBrush xmlns="http://schemas.microsoft.com/winfx/2006/xaml/presentation"&gt;#FF6495ED&lt;/SolidColorBrush&gt;</BrushSerialize>
              </TimeHighlighter5>
              <TimeHighlighter6>
                <StartTime>2025-01-01T09:00:00</StartTime>
                <EndTime>2025-01-01T17:00:00</EndTime>
                <Opacity>25</Opacity>
                <BrushSerialize>&lt;SolidColorBrush xmlns="http://schemas.microsoft.com/winfx/2006/xaml/presentation"&gt;#FF6495ED&lt;/SolidColorBrush&gt;</BrushSerialize>
              </TimeHighlighter6>
              <TimeHighlighter7>
                <StartTime>2025-01-01T09:00:00</StartTime>
                <EndTime>2025-01-01T17:00:00</EndTime>
                <Opacity>25</Opacity>
                <BrushSerialize>&lt;SolidColorBrush xmlns="http://schemas.microsoft.com/winfx/2006/xaml/presentation"&gt;#FF6495ED&lt;/SolidColorBrush&gt;</BrushSerialize>
              </TimeHighlighter7>
              <TimeHighlighter8>
                <StartTime>2025-01-01T09:00:00</StartTime>
                <EndTime>2025-01-01T17:00:00</EndTime>
                <Opacity>25</Opacity>
                <BrushSerialize>&lt;SolidColorBrush xmlns="http://schemas.microsoft.com/winfx/2006/xaml/presentation"&gt;#FF6495ED&lt;/SolidColorBrush&gt;</BrushSerialize>
              </TimeHighlighter8>
              <TimeHighlighter9>
                <StartTime>2025-01-01T09:00:00</StartTime>
                <EndTime>2025-01-01T17:00:00</EndTime>
                <Opacity>25</Opacity>
                <BrushSerialize>&lt;SolidColorBrush xmlns="http://schemas.microsoft.com/winfx/2006/xaml/presentation"&gt;#FF6495ED&lt;/SolidColorBrush&gt;</BrushSerialize>
              </TimeHighlighter9>

            </ChartControlProperties>
          </Properties>
          <ChartPanels>
            <ChartPanel>
              <Height>612</Height>
              <HoldChartTraderOrders>false</HoldChartTraderOrders>
              <IsMaximized>false</IsMaximized>
              <Right>
                <ChartScaleProperties xmlns:xsd="http://www.w3.org/2001/XMLSchema" xmlns:xsi="http://www.w3.org/2001/XMLSchema-instance">
                  <YAxisRangeType>Automatic</YAxisRangeType>
                  <AutoScaleDateRangeType>ScreenDateRange</AutoScaleDateRangeType>
                  <HorizontalGridlinesCalculation>Automatic</HorizontalGridlinesCalculation>
                  <HorizontalGridlinesIntervalType>Points</HorizontalGridlinesIntervalType>
                  <HorizontalGridlinesInterval>0</HorizontalGridlinesInterval>
                  <AutoScaleMarginType>Percent</AutoScaleMarginType>
                  <AutoScaleMarginLower>6</AutoScaleMarginLower>
                  <AutoScaleMarginUpper>6</AutoScaleMarginUpper>
                  <YAxisScalingType>Linear</YAxisScalingType>
                  <FixedScaleMaxSerialize>0</FixedScaleMaxSerialize>
                  <FixedScaleMinSerialize>0</FixedScaleMinSerialize>
                  <IsInverted>false</IsInverted>
                </ChartScaleProperties>
              </Right>
              <Left>
                <ChartScaleProperties xmlns:xsd="http://www.w3.org/2001/XMLSchema" xmlns:xsi="http://www.w3.org/2001/XMLSchema-instance">
                  <YAxisRangeType>Automatic</YAxisRangeType>
                  <AutoScaleDateRangeType>ScreenDateRange</AutoScaleDateRangeType>
                  <HorizontalGridlinesCalculation>Automatic</HorizontalGridlinesCalculation>
                  <HorizontalGridlinesIntervalType>Points</HorizontalGridlinesIntervalType>
                  <HorizontalGridlinesInterval>0</HorizontalGridlinesInterval>
                  <AutoScaleMarginType>Percent</AutoScaleMarginType>
                  <AutoScaleMarginLower>6</AutoScaleMarginLower>
                  <AutoScaleMarginUpper>6</AutoScaleMarginUpper>
                  <YAxisScalingType>Linear</YAxisScalingType>
                  <FixedScaleMaxSerialize>0</FixedScaleMaxSerialize>
                  <FixedScaleMinSerialize>0</FixedScaleMinSerialize>
                  <IsInverted>false</IsInverted>
                </ChartScaleProperties>
              </Left>
              <Overlay>
                <ChartScaleProperties xmlns:xsd="http://www.w3.org/2001/XMLSchema" xmlns:xsi="http://www.w3.org/2001/XMLSchema-instance">
                  <YAxisRangeType>Automatic</YAxisRangeType>
                  <AutoScaleDateRangeType>ScreenDateRange</AutoScaleDateRangeType>
                  <HorizontalGridlinesCalculation>Automatic</HorizontalGridlinesCalculation>
                  <HorizontalGridlinesIntervalType>Points</HorizontalGridlinesIntervalType>
                  <HorizontalGridlinesInterval>0</HorizontalGridlinesInterval>
                  <AutoScaleMarginType>Percent</AutoScaleMarginType>
                  <AutoScaleMarginLower>6</AutoScaleMarginLower>
                  <AutoScaleMarginUpper>6</AutoScaleMarginUpper>
                  <YAxisScalingType>Linear</YAxisScalingType>
                  <FixedScaleMaxSerialize>0</FixedScaleMaxSerialize>
                  <FixedScaleMinSerialize>0</FixedScaleMinSerialize>
                  <IsInverted>false</IsInverted>
                </ChartScaleProperties>
              </Overlay>
            </ChartPanel>
          </ChartPanels>
          <ChartAlerts />
          <TabName>@INSTRUMENT_FULL</TabName>
          <Type>ChartTab</Type>
        </Tab-e85edf1a4ed94b8bacd18201a3905566>
      </TabControl>
    </Chart-c5effcc8dc3a46e8bb49271b6bb2d6fd>
  </NTWindows>
</NinjaTrader>
